nexus_uploader.py
PyUpdater_Nexus_Plugin-0.3.dist-info/LICENSE
PyUpdater_Nexus_Plugin-0.3.dist-info/METADATA
PyUpdater_Nexus_Plugin-0.3.dist-info/WHEEL
PyUpdater_Nexus_Plugin-0.3.dist-info/entry_points.txt
PyUpdater_Nexus_Plugin-0.3.dist-info/top_level.txt
PyUpdater_Nexus_Plugin-0.3.dist-info/RECORD
