Metadata-Version: 2.1
Name: PyUpdater-Nexus-Plugin
Version: 0.3
Summary: Sonatype nexus plugin for PyUpdater
Home-page: https://github.com/pompompom/pyupdater-nexus-plugin.git
Author: Pierre Chevalier
Author-email: chevalier.pierre@gmail.com
License: UNKNOWN
Platform: Any
Classifier: Development Status :: 5 - Production/Stable
Classifier: License :: OSI Approved :: MIT License
Classifier: Programming Language :: Python :: 2.7
Classifier: Programming Language :: Python :: 3.5
Classifier: Programming Language :: Python :: 3.6
Classifier: Programming Language :: Python :: 3.7
Classifier: Intended Audience :: Developers
Classifier: Environment :: Console
